prefab_endpoints/__init__.py
django_prefab_endpoints-0.0.2.dist-info/METADATA
django_prefab_endpoints-0.0.2.dist-info/WHEEL
django_prefab_endpoints-0.0.2.dist-info/top_level.txt
django_prefab_endpoints-0.0.2.dist-info/RECORD
