Metadata-Version: 2.1
Name: django-prefab-endpoints
Version: 0.0.2
Summary: Quick and basic endpoints for Django
Home-page: https://github.com/johnsynnott/django-prefab-endpoints
Author: John Synnott
Author-email: johnsynn@gmail.com
License: UNKNOWN
Platform: UNKNOWN
Classifier: Programming Language :: Python :: 3
Classifier: Operating System :: OS Independent
Requires-Python: >=3.6
